spec_mcp/cli.py
spec_mcp/dashboard.py
spec_mcp/db.py
spec_mcp/mcp_main.py
spec_mcp/mcp_server.py
spec_mcp/queries.py
spec_mcp/server.py
spec_mcp/verification.py
spec_mcp/api/__init__.py
spec_mcp/api/features.py
spec_mcp/api/fragments.py
spec_mcp/api/metrics.py
spec_mcp/api/specs.py
spec_mcp/api/verify.py
spec_driven_mcp-0.0.8.dist-info/METADATA
spec_driven_mcp-0.0.8.dist-info/WHEEL
spec_driven_mcp-0.0.8.dist-info/entry_points.txt
spec_driven_mcp-0.0.8.dist-info/top_level.txt
spec_driven_mcp-0.0.8.dist-info/RECORD
