Metadata-Version: 2.4
Name: spec-driven-mcp
Version: 0.0.8
Summary: MCP server for specification-driven development: manage feature specs, requirements, acceptance criteria, test linkage and status.
Author: Tiago Melo
License-Expression: MIT
Requires-Python: >=3.11
Requires-Dist: mcp[cli]
Requires-Dist: pydantic>=2.7
Requires-Dist: uvicorn
Requires-Dist: typer
Requires-Dist: rich
Requires-Dist: sqlite-utils>=3.36
Requires-Dist: platformdirs
